asyncpgsa/__init__.py
asyncpgsa/connection.py
asyncpgsa/log.py
asyncpgsa/pgsingleton.py
asyncpgsa/pool.py
asyncpgsa/transactionmanager.py
asyncpgsa/version.py
asyncpgsa/testing/__init__.py
asyncpgsa/testing/mockconnection.py
asyncpgsa/testing/mockpgsingleton.py
asyncpgsa/testing/mockpool.py
asyncpgsa/testing/mockpreparedstmt.py
asyncpgsa/testing/mocktransactionmanager.py
asyncpgsa-0.24.0.dist-info/METADATA
asyncpgsa-0.24.0.dist-info/RECORD
asyncpgsa-0.24.0.dist-info/WHEEL
asyncpgsa-0.24.0.dist-info/top_level.txt
