Metadata-Version: 2.1
Name: asyncpgsa
Version: 0.24.0
Summary: sqlalchemy support for asyncpg
Home-page: https://github.com/canopytax/asyncpgsa
Author: nhumrich
Author-email: nick.humrich@canopytax.com
License: Apache 2.0
Platform: UNKNOWN
Requires-Dist: asyncpg
Requires-Dist: sqlalchemy
